{"id":"A31crlYMv4QUmQ7mE8rwH","created":"2023-08-15T12:03:20.004Z","updated":"2023-08-15T12:03:20.004Z","name":"@activepieces/piece-delay","displayName":"Delay","logoUrl":"https://cdn.activepieces.com/pieces/delay.png","description":"","projectId":null,"version":"0.3.1","minimumSupportedRelease":"0.5.0","maximumSupportedRelease":"99999.99999.9999","auth":null,"actions":{"delayFor":{"name":"delayFor","displayName":"Delay For","description":"Delays the execution of the next action for a given duration","props":{"unit":{"displayName":"Unit","description":"The unit of time to delay the execution of the next action","required":true,"options":{"options":[{"value":"seconds","label":"Seconds"},{"value":"minutes","label":"Minutes"},{"value":"hours","label":"Hours"},{"value":"days","label":"Days"}]},"defaultValue":"seconds","type":"STATIC_DROPDOWN"},"delayFor":{"displayName":"Amount","description":"The number of units to delay the execution of the next action","required":true,"validators":[{"type":"NUMBER"}],"defaultProcessors":[null],"defaultValidators":[{"type":"NUMBER"}],"type":"NUMBER"}},"requireAuth":true,"sampleData":{}},"delay_until":{"name":"delay_until","displayName":"Delay Until","description":"Delays the execution of the next action until a given timestamp","props":{"delayUntilTimestamp":{"displayName":"Date and Time","description":"Specifies the date and time until which the execution of the next action should be delayed. It supports multiple formats, including ISO format.","required":true,"defaultProcessors":[null],"defaultValidators":[{"type":"DATE_TIME"}],"type":"DATE_TIME"}},"requireAuth":true,"sampleData":{}}},"triggers":{}}